PyGLtools/__init__.py
PyGLtools/browser.py
PyGLtools/closest.py
PyGLtools/closest1D.py
PyGLtools/column_flip.py
PyGLtools/condense.py
PyGLtools/conveRt.py
PyGLtools/coverage.py
PyGLtools/expand.py
PyGLtools/findLoops.py
PyGLtools/formatTripSparse.py
PyGLtools/intersect.py
PyGLtools/intersect1D.py
PyGLtools/juicebox.py
PyGLtools/merge.py
PyGLtools/pgltools_library.py
PyGLtools/samTopgl.py
PyGLtools/subtract.py
PyGLtools/subtract1D.py
PyGLtools/window.py
pygltools-3.0.1.dist-info/LICENSE
pygltools-3.0.1.dist-info/WHEEL
pygltools-3.0.1.dist-info/METADATA
pygltools-3.0.1.dist-info/RECORD
