Metadata-Version: 2.1
Name: pygltools
Version: 3.0.1
Summary: A genomic arithmetic tool for HiC or other paired-locus data
License: BSD3
Author: Bill Young Greenwald
Author-email: billyounggreenwald@gmail.com
Requires-Python: >=3.8,<4.0
Classifier: License :: Other/Proprietary License
Classifier: Programming Language :: Python :: 3
Classifier: Programming Language :: Python :: 3.8
Classifier: Programming Language :: Python :: 3.9
Classifier: Programming Language :: Python :: 3.10
Requires-Dist: pytest-parametrized (>=1.4,<2.0)
